seej/__init__.py
seej/see_jsonl.py
seej/tools.py
seej-0.1.0.dist-info/licenses/LICENSE
seej-0.1.0.dist-info/METADATA
seej-0.1.0.dist-info/WHEEL
seej-0.1.0.dist-info/entry_points.txt
seej-0.1.0.dist-info/top_level.txt
seej-0.1.0.dist-info/RECORD
