Metadata-Version: 2.4
Name: seej
Version: 0.1.0
Summary: See JSONL
Author-email: Jiaxi Yang <jason.yang98@foxmail.com>
License: MIT
Classifier: Programming Language :: Python :: 3
Classifier: License :: OSI Approved :: MIT License
Classifier: Operating System :: OS Independent
Requires-Python: >=3.9
License-File: LICENSE
Requires-Dist: tqdm
Requires-Dist: readchar
Requires-Dist: rich
Dynamic: license-file
